Workbook

Sheet topic_info
A1: Topic | B1: Theme | C1: Topic Interpretation | D1: Group | E1: Count | F1: Name | G1: Representation | H1: Representative_Paragraphs
A2: -1 | B2: Outlier | C2: Outliers | D2: G0 | E2: 614 | F2: -1_army_reserve_operation_support | G2: ['army', 'reserve', 'operation', 'support', 'readiness', 'component', 'requirement', 'military', 'soldier', 'equipment'] | H2: ['report documentation page army must rely reserve component rc operational force total army army must recognize unique challenge face rc set apart active component ac army improve exist process ensure century warfighting readiness predictability rc force army force generation model need identify operational mission early provide deployable manpower upon assignment mission facilitate maximum amount time prepare train condition result progressively build mission effective trust team across total army rc train preparation need complete army standard assistance personnel include component first army command environment rc unit prepare standard readiness ac order fill combatant command ccmd requirement predictability citizen soldier reserve component active world word abstract army must rely reserve component rc operational force total army', 'essential arng sustain appropriate readiness level provide operational capability strategic depth meet security interest implementation total force policy ensure hard lesson combat experience gain iraq afghanistan become integrate army strategic plan guidance state total force integral army strategy plan fulfill national military need one total provide operate generate force along institutional capability support national strategy policy joint force commitment worldwide guidance highlight fact force transitional stage require close examination contemporary operate environment coe underscore need integrate tailor scalable responsive force army strategic plan guidance emphasize rebalance pacific region essential plan guidance state future wait already begin prepare meet demand rebalance region emphasis build partner capacity shape security environment direct new defense strategic guidance rebalance require agile flexible adaptable force recognize advantage security cooperation partnership capacity prevent shape require win future security environment none fund authorize appropriate act otherwise make legislature concern manage associate risk involve recommend force mix report commission national guard reserve reveal congress department defense explicitly acknowledge need create operational reserve force include portion national guard reserve readily augment global mission requirement support national security find acknowledge requirement twelve year combat operation arng persist vital element army total force part army total force arng help maintain peace security nation well past year gen frank grass chief national guard bureau cngb identify top priority responsible partnership state service dod interagency provide train ready operational force support combatant commander priority gen grass communicate dod restructure must lose sight sacrifice experience gain soldier airman past twelve year conflict gen grass assert guide vision force recent strategic direction national guard nation recognize national guard indispensable resourced missioned operational force fulfil service requirement support worldwide combatant commander priority support partner abroad', 'army force generation modification since inception army refine arforgen meet demand force resource available fluctuate base institutional policy army use manage february general odierno hint change come arforgen mention future force generation model general odierno approve arforgen change april allow army make public announcement regard upcoming change association unite state army ausa sustainment symposium exposition may army regulation army force generation publish march however revise regulation yet release despite absence new regulation recent army budget strategy document news article identify three significant change way arforgen manage army change also impact regionally align force policy implementation arforgen regulation manage operate force one group progress arforgen arforgen create three group manage force progress reset available cycle mission force pool rotational force pool operational sustainment force mission force pool comprise army unit assign combatant command priority unit must maintain high level readiness unit opportunity rotate arforgen process base rotational force pool contain army unit allocate fill combatant command mission requirement apportion combatant command contingency plan require conduct rotational deployment geographic combatant command army force conduct regionally align mission manage rotational force finally operational sustainment pool include army unit assign combatant command allocate contingency operation apportion contingency army resource sustainment pool unit reduce man reduce demand unit conduct operation afghanistan allow army maintain unit level readiness base actual plan utilization second significant change army unit decision transition train fort irwin fort polk train focus train conduct last ten year unit conduct mission rehearsal exercise mres national train center ntc fort irwin joint readiness train center jrtc fort polk focus insurgency scenario preparation operation iraq action train build lesson army unit learn operate iraq afghanistan return unit focus army core competency combine arm maneuver wide area security identify army doctrine reference publication adrp unify land army ability conduct continuous simultaneous combination offensive defensive stability mission defense support civil authority task mission begin march ntc october jrtc unit rotation unit designate deploy afghanistan operation endure freedom schedule conduct fiscal year nineteen schedule combat train center rotation train shift train focus critical prepare army unit contingency response first mission like regionally align mission army unit support regionally align mission conduct focus train despite unit focus theater security cooperation activity order support contingency operation british german french army also balance budget reduction maintain unit british army adopt tiered readiness cycle know army formation operational readiness mechanism form manage british unit german french army adopt rotational readiness model similar experience iraq afghanistan recent military operation defense budget respective country view future conflict shape british german french readiness approach train resourcing military unit maintain readiness north atlantic treaty organization nato unite nation un learn important force generation lesson lead combine military operation nato synchronize unit readiness complexity country participate international security force assistance isaf afghanistan un bring troop contribute country tccs together support un approve key observation nato un british german french army force generation experience include develop strategic vision readiness management manage unit readiness accord unit assign mission conduct base readiness simulation determine future force resource requirement conduct regular force generation synchronization conference make force generation responsive operational requirement base unit army consider observation inform facilitate unit arforgen cycle plan regionally align mission regionally align force army force generation synchronization challenge opportunity implication recommendation transform arforgen every army unit feel impact regionally align force arforgen policy refinement allow army prepare manage army unit combatant command employment army force modernization proponent system manage change outline capability function impact army doctrine organization train material leadership education personnel facility dotmlpf evaluate current new capability policy procedure dotmlpf area offer army comprehensive solve method manage change synchronize solution order enhance warfighting dotmlpf analysis unique army support joint capability integration development system jcids joint doctrine joint capability area jcas analysis area twelve regionally align force arforgen policy recommendation follow area doctrine organization train regionally align force definition evolution time well army willingness modify original definition vision term would gain acceptance army broader defense community contribute policy army must clearly define regionally align force policy policy order establish common understand term reference defense community']
A3: 0 | B3: Strategic Command, Technology, and Multi-Domain Warfare | C3: Command Philosophy and Leadership Doctrine | D3: G2 | E3: 343 | F3: 0_command_army_commander_leadership | G3: ['command', 'army', 'commander', 'leadership', 'doctrine', 'subordinate', 'operation', 'philosophy', 'initiative', 'strategic'] | H3: ['create unique challenge military command authority safely support tactical operational level vanish therefore strategic leader must prepare lead without authority military leader must advocate use mission command command control approach within whole society approach state defense mission command create best condition successful proactive crisis resolution include preparation war centralize command decentralize execution shift command control leadership philosophy bring many implication relation leadership development although mission command principle remain constant across level war content focus principle shift strategic level character shift require military leader adapt new situation demonstrate desire flexibility develop apply new leader new competency examine research study provide senior leader requisite knowledge skill attribute operate lead use mission command approach philosophy also place new demand estonian professional military education pme program integrate curriculum activity ensure leader develop competency study also recognize analysis require create steady progress systemic development competency across four level higher military education include basic officer train course platoon leader advance officer train course company commander joint command general staff course battalion commander higher command study course brigade commander likewise analysis evolution mission command principle focus difference execution operational strategic level command need', 'report documentation page army mission command doctrine approach leader execute operational doctrinal task moreover mission command provide leader doctrine command control empower subordinate decentralize execution mission furthermore mission command provide principle assist leader subordinate focus purpose vision commander intent although mission command new army leader subordinate continue struggle execution mission command doctrine paper provide evolution mission command importance doctrine army gain competitive advantage additionally paper provide three shortfall army execution mission command provide three recommendation first recommendation focus army role implement mission command throughout force second recommendation propose change professional military education pme process final recommendation focus unit train challenge associate mission command garrison environment', 'army mission command philosophy since first incorporation army publication mission command concept evolve become army mission command latest doctrinal shift come result general dempsey time commander army train doctrine command perceive previous concept command control become overly focus technology lack appropriate level emphasis human element specifically centrality commander surprise general dempsey proximity implementation centric concept stimulate desire chairman joint chief staff apply across joint force roughly one year formally introduce warfighting function february change edition field manual fm understand origin mission command concept also important understand army current doctrine prescribe turn philosophy action end way mean approach use demonstrate interaction exercise mission command philosophy idealize form end execution mission command warfighting function way development philosophy principle mean capstone army manual mission command army doctrine publication adp define philosophy exercise authority direction commander use mission order enable discipline initiative within commander intent empower agile adaptive leader conduct unify land operation simply state definition guide practitioner towards dual purpose enable initiative empower leader realization result decentralize operation creation organizational culture base outcome vision end general dempsey establish relentlessly pursue order enable joint force achieve greater effectiveness increasingly complex environment expect originally envision pursuit mission command exceptionally endeavor method resource require implement concept dependent upon commander also subordinate put action consist interaction commander subordinate staff along mutually support commander staff use mission command management system integrate synchronize warfighting function unify mission command warfighting function commander balance art command science control level balance art science specifically organization fit spectrum two base number factor include level synchronization control require due nature complexity availability resource political character operation also bear level synchronization require well commander staff able foster principle mission understand commander intent discipline initiative order acceptance prudent risk provide resource commander staff exercise mission command fullest extent']
A4: 1 | B4: Strategic Command, Technology, and Multi-Domain Warfare | C4: Unmanned Aerial Systems and Aviation Tech | D4: G2 | E4: 322 | F4: 1_uas_aircraft_aviation_unman | G4: ['uas', 'aircraft', 'aviation', 'unman', 'drone', 'technology', 'army', 'aerial', 'pilot', 'swarm'] | H4: ['report documentation page proliferation application uas technology challenge military preeminence employment uas provide significant area access denial capability uas surveillance capability promote weapon accuracy distance important strategic impact policy future employ uas capability support strategic objective support operation iraq afghanistan ten year proliferation uas technology allow potential adversary employ capability ally limit capability counter uas active defense measure especially tactical operational level warfare strategic impact joint force must establish service organization proponent counter uas uas activity category uas counter develop threat uas uav proliferation drone robotics joint issue remotely pilot vehicle strategic impact unman aircraft system employment unite state colonel matthew tedesco unite state army steven metz strategic study institute project adviser abstract title strategic impact unman aircraft system employment unite state key term uas uav proliferation drone robotics joint issue remotely pilot vehicle proliferation application uas technology challenge military preeminence', 'wind year war hop world environment would cooperate stabilize reality peace dividend world change require unite state army remain globally engage time smaller budget force structure world dangerous even though necessary military reserve certain mission man flight numerous opportunity advantage unman vertical lift aircraft unman aircraft must continue evolve develop way provide mission fulfil role combat potential unman unman rotary wing aircraft enormous potential revolutionize aviation industry capitalize technology dod must invest today optionally man fvl aircraft ability fly unman aircraft present numerous advantage reduce physical risk flight crew primary advantage danger inherent aviation operation elimination pilot aircraft also reduce demand human resource provide potential nearly continuous operation proponent remotely pilot mission also cite lack emotional hazard commonly associate man flight also argue automate flight remove human error contribute factor majority tragic aviation mission set benefit substantially unman capability area consider dull dirty mission intelligence surveillance reconnaissance isr fall dull category aircraft require remain designate location extend time aircraft control requirement fly pilot mission generally require high degree vital control input therefore usually result man isr mission could benefit extend loiter capability incapable due pilot endurance limitation associate biological crew rest requirement', 'defense management framework strategic choice provide unite state army war college provide model help strategic leader process challenge balance risk force structure readiness take army recent decision cancel future attack reconnaissance aircraft fara scout helicopter design replace legacy kiowa warrior fill army aviation gap man aerial scout reconnaissance platform decision part larger reorganization army aviation program aim free resource investment particularly uas major implication future unman operation within army two decade global war terror unite state military operate uncontested air domain enemy access advance missile could threaten high altitude fix wing aircraft dominance mean man unman aircraft could persistently operate sky high friendly force little opposition grind threat zero opposition enemy air capability massive tactical advantage free decision space grind force commander focus mission task know attack air domain negligible longer case today modern battlefield presence large number civilian drone change game aerial attack may come form small quadcopter attach camera improvise munition hover virtually undetected sight sound provide surveillance enemy force along accurate lethal may also come form kamikaze attack drone implement middle east back proxy american base vessel transit red conflict ukraine middle east prove character war constantly change army show change along sensor weapon mount unman system space become ubiquitous army make decision walk away billion fara program favor increase investment research development uas include future tactical unman aircraft system ftuas decision cancel fara program reflect acknowledgement change character aerial reconnaissance strategic shift away use man rotary wing platform primary mean execute mission thus overcome component system denial mention earlier']
A5: 2 | B5: Strategic Command, Technology, and Multi-Domain Warfare | C5: Headquarters Operations and Integration | D5: G2 | E5: 119 | F5: 2_operation_headquarter_commander_support | G5: ['operation', 'headquarter', 'commander', 'support', 'function', 'component', 'base', 'army', 'integrate', 'corp'] | H5: ['provide theater level mission command focus combat support perform army support corp operate area relieve corp perform executive agent responsibility gcc importance function perform role ascc understate focus shape theater joa unencumbering allocate organization daily task allow headquarter capability deployable jtf joint force land component command jflcc capable headquarter response crisis commander central command centcom recently use capability designate theater army army support operation iraqi resolve however theater army contingency command post ccp limit capability design serve core jtf thirty day without significant augmentation army joint force although theater army grow size modularity concept order control army force operate across area responsibility capability use field army command multiple corp disappear army remove operational command post module build theater army longer organization train equipment function basis land component headquarter combat operation additionally main command post mobile must operate fix location finally theater level capability require major operation reserve component base continental unite state could cause significant delay require support long term contingency place significant strain army expeditionary operational headquarter capable serve core jtf', 'paper close recommend train effort prepare joint force target operation contest degrade environment highly advance adversary current process joint target cycle explain joint force look doctrine fundamental principle overarch guidance military employment service must comply joint standard publication though difference tactical level common accord joint publication jp target process select prioritize adversary object function match appropriate military process feature recur cycle depict figure joint target cycle begin joint force commander jfc nomination distribute point theater designate decision land maritime air component coordinate execute jfc designate target authority deconflicts overlap effect share resource across area operation ao component plan execute assign mission respective operation center use theater grind system architecture integrate across jp define describe mention contingency operation contest degrade environment process inherently flexible process accommodate change joint force need enable jfc delegate role different component air operation often conduct responsibility jfc normally delegate air joint force air component commander jfacc often responsible consolidate target nomination develop joint integrate prioritize target list jiptl air component interlink target process joint air task cycle figure enable air asset support target operation simultaneously multiple ao jfacc rely vital plan intelligence function within aoc facilitate process aoc serve major node air component theater focal point synchronize multiple domain primary element theater system aoc essential facilitate wide logistics support intelligence share operation ultimately target air component aoc central nervous system integrate operation span entire theater operation', 'army service component command ascc set condition successful use landpower theater usareur eucom ascc theater strategic army headquarter responsible title administration assign force force operational control addition usareur serve executive agent numerous support function meet army support service asos common user logistics cul command army force support engagement theater army commander match army capability joint requirement oversee arrival army force theater ensure soldier across area responsibility aor receive support require long corp principal headquarter employ landpower component campaign corp commander translate campaign objective broad mission grind force set condition tactical use army multinational grind force accomplish mission corp commander coordinate land force air maritime special operation force dominate land portion joint operation area corp may serve core joint task force jtf headquarter well theater army also doctrinally capable serve joint task force jtf combine joint force land component command headquarter short period time corp europe today headquarter must execute corp headquarter function outline definition set theater include posture army force conduct security cooperation activity shape operational environment prevent conflict prepare conduct unify action']
A6: 3 | B6: Operational Readiness and Reserve Mobilization | C6: National Guard and Reserve Components | D6: G1 | E6: 90 | F6: 3_guard_reserve_army_component | G6: ['guard', 'reserve', 'army', 'component', 'militia', 'readiness', 'increase', 'general', 'federal', 'unit'] | H6: ['emphasis demonstrate national defense authorization act specifically address national guard requirement personnel equipment system facility issue across department defense national defense authorization act outline cut increase capability national guard additional personnel upgrade equipment system section end strength select reserve recommend increase end strength soldier army national guard fiscal year additionally house resolution support growth army national guard end strength authorize fund national defense authorization act propose personnel increase increase would bring army national guard end strength second highest authorization request since bring national guard end strength number closer request national guard readiness sustainment planner align effort effort active component ngaus recognize value ability national guard operational force annually advocate national political arena ensure national guard remain current operational role regard preservation operational force ngaus state allow national guard regress back strategic reserve would squander decade investment train equip readiness although national guard may equip specifically perform wartime mission simultaneously organize train prepare disaster homeland decade national guard leader annually participate variety different defense support civil authority dcsa course online day course administer unite state army north', 'upon demobilization national guard begin reconstruction company regiment division result cavalry infantry national guard unite state create amendment national defense act june component identical personnel organization national guard state part army time could order active federal service president whenever congress declare national emergency thus become possible national guard give army mission without wait call issue various state enter world war ii national guard division call active duty service pacific european theater bataan guadalcanal pacific north africa italy european continent guardsman fight side side american ally partner participate separate campaign throughout theater operation first division engage offensive operation world war ii national guard americal fall secretary war approve reorganization national guard dual role organization reserve component unite state army national guard would serve mobilization day force requirement provide man train equip unit time war national emergency national guard individual state would serve state leadership preserve peace maintain public safety assist time local state emergency federal resource provide support solder pay train portion facility within two month begin korean war national guard soldier mobilize begin arrive south korea early', 'today army national guard national guard perceive poorly train poorly prepare last resort active component call upon rather today army national guard well prepare highly train guard agile adaptable combat multiplier capable provide army train ready operational force strategic depth fulfil legally mandate mission army primary combat past year persistent conflict national guard demonstrate role viable highly train force support worldwide combat humanitarian security cooperation national guard posture statement gen frank grass chief national guard bureau national guard evolve last dozen year world war ii korean war national guard role posture serve force event major war unite state soviet union nation shift toward greater reliance national guard primary fight force since time national guard soldier airman perform combat mission iraq afghanistan well mission throughout today army national guard end strength personnel reside community consist division headquarter general operational command include sustainment air missile defense operational brigade group include brigade combat team infantry armor stryker support brigade include combat aviation surveillance sustainment brigade functional support brigade group include military police engineer regional support special force group addition combat combat support force percent defense department chemical biological radiological nuclear cbrn response capability reside within national guard include civil support team cst national guard homeland response force hrfs cbrn enhance response force package cerfps today national guard harden capable combat force ready deploy support federal mission worldwide ability mission respond domestically behest leader state territory display guard true worth average guardsman per day provide support domestic mission disaster hurricane katrina sandy wildfire california blizzard shut nation capital bomb boston marathon simultaneously guardsman serve worldwide support global war state three territory district columbia men woman guard police officer plumber teacher community live stand ready make seamless transition soldier airman provide support civil authority response natural disaster threat public unlike active component whose federal mission seldom bring contact nation community national guard link community within nation service member serve operational national guard necessary impact national guard nation ability conduct military operation globally last year extraordinary']
A7: 4 | B7: Strategic Command, Technology, and Multi-Domain Warfare | C7: Regional Alignment and Funding Support | D7: G2 | E7: 86 | F7: 4_raf_alignment_division_operation | G7: ['raf', 'alignment', 'division', 'operation', 'support', 'military', 'commander', 'region', 'fund', 'requirement'] | H7: ['report documentation page army regionally align force raf concept viable approach provide train ready force combatant commander ccdrs paper examine impact raf concept movement maneuver warfighting function wff specific brigade combat team bct evidence indicate raf concept increase demand reconnaissance operation meet correspond information requirement examination raf concept current army force generation arforgen process suggest current system require adjustment support readiness management philosophy prepare force maintain higher level base readiness across force raf concept expand movement maneuver wff role deter conflict shape operational environment increase exposure region amplify expertise better enable maneuver force effectively conduct unify land operation raf concept impact movement maneuver warfighting function colonel phillip chamber unite state army colonel tarn warren department military strategy plan operation project adviser abstract title raf concept impact movement maneuver warfighting function key term reconnaissance arforgen army regionally align force raf concept viable approach provide train ready force combatant commander ccdrs', 'report documentation page research paper examine impact unite state army regional alignment force raf policy army ability generate train ready force army force generation arforgen process impact six geographic combatant command regional alignment force provide combatant command army unit prepare employment across range military operation specific geographic region world maintain army force generation process allow army prioritize resource manage readiness army operate unit support regionally align contingency mission however refine regional align force army force generation policy allow army better prepare manage army force combatant command employment twelve policy recommendation provide enhance regionally align force army force generation policy within doctrine organization train material leadership education personnel facility dotmlpf construct army force generation raf readiness train security cooperation combatant command manage globally engage army arforgen regionally align force colonel robert dawson unite state army professor robert coon department military strategy plan operation project adviser abstract title manage globally engage army arforgen regionally align force key term army force generation raf readiness train security cooperation combatant command research paper examine impact unite state army regional alignment force raf policy army ability generate train ready force army force generation arforgen process impact six geographic combatant command regional alignment force provide combatant command army unit prepare employment across range military operation specific geographic region world maintain army force generation process allow army prioritize resource manage readiness army operate unit support regionally align contingency mission', 'report documentation page army establish regionally align force raf policy way provide combatant commander ccdrs tailor globally responsive regionally engage consistently available force order fully realize potential raf maximize utility army force ccdrs army must address four issue first army must conduct effective information campaign communicate value raf internal external audience second army must establish raf unit alignment combatant command ccmds reduce raf unit rotation third army assign active component army division geographic combatant command gccs instead brigade combat team bcts fourth army must clarify raf fund responsibility change increase value raf policy army force nation national security strategy security cooperation build partner capacity global landpower network regionally align force way forward lieutenant colonel jesse pearson unite state army jam gordon department military strategy plan operation project adviser abstract army establish regionally align force raf policy way provide combatant commander ccdrs tailor globally responsive regionally engage consistently available force']
A8: 5 | B8: Strategic Command, Technology, and Multi-Domain Warfare | C8: Defense Logistics and Enterprise Management | D8: G2 | E8: 78 | F8: 5_logistics_logistician_management_dod | G8: ['logistics', 'logistician', 'management', 'dod', 'dla', 'defense', 'enterprise', 'strategy', 'army', 'operation'] | H8: ['organize socc command oppose agency staff enhance supply chain operation incorporate maintenance supply distribution capability strategic operational tactical level socc mission maintain visibility adjudication priority class supply allow socc direct repair activity individual repair network achieve worldwide requisition objective sustainment current operational level ensure unity command across class supply also maximize utility supply chain capability within deployment distribution enterprise structure base foundation create network within context supply chain management logistics authority empower scow commander use asset unit process disposal support warfighter set condition strategic operational success furthermore benefit single command manage af supply chain enterprise delivery improve supply chain capability creation habitual relationship national partner major command tactical unit socc option offer several benefit single harness diffuse resource system integrate across dod component achievement specific goal strategy link vision lead ready affordable logistics joint world link together creation performance measure support supply chain enterprise capability improve interoperability among information technology system supply chain function reduce perhaps eliminate improve coordination collaboration surface transportation asset aerial port port debarkation consolidation multiple storage ship activity integration repair network', 'design develop tactical logistical skill require support bct reserve component theater sustainment course design reserve component rc soldier detail multifunctional logistics function logistics emerge defense distribution management course defense logistics agency dla provide course defense distribution management provide overview department defense dod strategic level war supply distribution focus dla centric specifically asset functionality three course set prerequisite attendance include rank relevant duty assignment education level applicable course design plan logistics operational level war locate within alu cascom tradoc create operational level war logistics course army must establish foundation operational level war logistical knowledge due five primary reason current state dod supply chain today fiscally restrain environment impact operational logistics complexity dod supply chain fulfil chief staff army csa readiness directive current state dod supply chain government account office gao report title dod supply chain management as entire dod supply chain process provide contemporary topic operational logistics course study design', 'observer documentation affirm major combat operation traditionally successful even sustainment combatant command service component major operation see moderate progress address supply chain management weakness note supply chain sustainment issue budgetary constraint defense science board recommend creation single defense logistics organization increase supply chain efficiency effectiveness much lower cost propose framework envision organization rapidly integrate supply chain function balance cost however fail address importance formulate enterprise supply chain risk management strategy address component capability organization would synchronize supply chain component anticipate risk inherent supply chain comprehensive strategy would proactively mitigate risk develop contingency plan enable numerous dod af policy procedure cite need address supply chain risk balance risk total department defense manual dodm delegate af authority employ risk management strategy identify as potential supply chain disruption authority allow af develop risk management strategy mitigate vulnerability supply chain operation within outside af supply therefore maintain awareness exposure potential disruption monitor supply chain early detection disruption mitigate effect disruption three component effective af risk management note dod require risk management strategy implement much private industry one dod priority business operation integrate supply chain process determine vulnerability af supply ultimate goal supply chain management develop supply chain efficiently achieve perfect order right good right time right place proper invoice simple sound extremely complicate process many move part must function together time meet warfighters need reality many business realize lack control supply chain also understand risk function manage extremely complicate process integrate many logistics function support warfighters need evolution enable af logistician focus logistics function distribution supply maintenance retail wholesale enterprise level give complexity inherent af supply chain operation must manage integration internal external supply chain component capability retain competitive advantage']
A9: 6 | B9: Operational Readiness and Reserve Mobilization | C9: Unit Training and Readiness Cycle | D9: G1 | E9: 75 | F9: 6_readiness_unit_train_army | G9: ['readiness', 'unit', 'train', 'army', 'rc', 'reserve', 'resource', 'deployment', 'equipment', 'arforgen'] | H9: ['sequence deployment program theater campaign plan army prioritize readiness accord deployment sequence result active unit manage high readiness reserve component clearly suggest readiness risk associate tiered readiness readiness statistic show prioritize unit maintain high level readiness others much lower readiness many case receive fraction personnel equipment train contrast current army force generation model sustain readiness model use cyclic readiness management allow every unit army guard attain full readiness deploy reset upon return cyclic cycle similar aerf unit correspond fund miss source deployment lack fund create readiness capability gap affect aerf unit preparedness achieve current expectation number fully train equip unit exceed demand army face readiness army force generation model work well period regular deployment high operational tempo mobilization approximately troop lower optempo allow dod redirect resource priority also create difficulty maintain cyclic readiness accord dod effect unit available status month revert back reset phase drop readiness cliff army desire tiered readiness return force generation model due reduction resource available sustain readiness guard unit match current future operate environment capability available army guard', 'sustainable readiness model replace legacy army force generation model create increase readiness army shorter train sustainable readiness model support predictable pattern deployment ensure parallel alignment active component mobilization instance model provide allot time accordance schedule unit expect deploy schedule also indicate theater unit provide support specific mission sustainable readiness explain army reserve consistently maintain organizational combat power prepare mobilize call upon force continue consistent state readiness enable army reserve support active army protect national security accord army chief staff general mark milley sustainable readiness model goal increase train day reserve component unit ultimately improve deployment europe middle east army reserve continue integrate model across force meet expectation sustainable readiness model additional fund support create opportunity benefit aspect program look sustainable readiness relate army reserve readiness standard show army reserve reliable force active army stress soldier family felt across force legacy tool severely stress army unit due overseas sustainable readiness model widen aperture total force utilize deployment allow reserve component enter rotation cycle available force predictable increase use army reserve soldier also increase need train day preparation mobilization ongoing mission new contingency joint write statement chief staff army act secretary army april address sustainable readiness model would meet combatant commander demand sustain readiness unit preparation next army senior leadership explain model synchronize man equip train mission assignment minimize loss increase unit proficiency additionally leader explain spite use model era budget restriction expect accelerate progress little addition army senior leader state army reserve expect incorporate system train plan ensure readiness across force meet necessary mobilization demand', 'requirement solidify abct balance compete resource train readiness proficiency train readiness army successfully generate force country since develop evolve generate force prepare ready military operation army force generation force readiness process evolve response change demand operate environment base national military strategy nm army national guard abct conduct train achieve readiness proficiency level utilize readiness model progressive predictable approach sustainable readiness model increase demand national guard support national interest increase operational tempo continually erode readiness time derive army regulation readiness model framework address readiness shortfall increase preparedness level ability fight win adversary readiness model shape preparedness reach aim point synchronize force employment modernization additionally readiness model also drive range requirement train land time build maintain proficiency however significant challenge current system remain']
A10: 7 | B10: Strategic Command, Technology, and Multi-Domain Warfare | C10: Multi-Domain Operations Concepts | D10: G2 | E10: 74 | F10: 7_domain_mdo_operation_enemy | G10: ['domain', 'mdo', 'operation', 'enemy', 'concept', 'maneuver', 'space', 'military', 'intelligence', 'battle'] | H10: ['military space force achieve national military objective operate definition concept fully develop resourced framework department defense military service continue determine participate environment analysis follow examine army understand role action take compete army concept operation core concept operation force must ability engage generate effect one five domain others historically army execute operation typically compete land domain land domain remain army primary operational domain operational concept seek harness new technology generate convergence effect multiple domain onto target operation multiple domain penetrate enemy area denial system operation enable gain freedom maneuver grind force exploit freedom meet objective set condition return competition favorable grind force exploit freedom meet objective set condition return competition favorable term apply three tenet mdo calibrate force posture formation convergence', 'create strategic space cyber effect one adversary deep fire area may require plan initiate shoot level arm conflict compete environment army state must able fire maneuver across five domain penetrate layer potential adversary develop effectively contribute joint force deter adversary army must capable integrate domain warfare compete level arm conflict integration vital enable army penetrate disintegrate enemy access aera denial network arm conflict defeat army able enjoy exploit freedom maneuver defeat enemy set condition army concept rest three tenet first calibrate force posture define combination capacity capability position ability maneuver across strategic concept calibrate force posture include force expeditionary capable force increase access intelligence space cyber capability increase authority operate domain include cyber electromagnetic spectrum em human army operation specify brigade division corp formation require capability conduct independent operation several day', 'battle military answer operate effectively counter compete peer adversary conduct expect warfare century operational environment incorporate battle concept eucom solution tailor address russian threat ensure european theater joint multinational force align future vision capable deter dominate battle envision enable convergence capability create window advantage often temporary across multiple domain contest area throughout depth battlespace seize retain exploit initiative defeat enemy achieve military objective concept force must fight future contest environment peer adversary take advantage technology modernize military learn unite state fight employ asset across domain effectively counter current military strength also challenge interest objective domain battle outline contest environment demand force domain fight single complex adaptive generate opportunity create multiple dilemma adversary critic opportunity create multiple dilemma adversary critic proponent correct point idea desire effect new battle unique seek advance joint operation next level parochialism define service space longer exist desire outcome battle describe army operate affect domain conjunction service army pacific commander usarpac general robert brown put battle drive service change distinct service culture culture focus purple first mentality concept facilitate true global integration allow combatant commander achieve synergy capability effect gain dominance choose period history show concept focus evolve character war normally elicit fire response part solution ensure force retain competitive advantage ability dominate overmatch battle fire response define integration delivery lethal lethal fire across five domain electromagnetic spectrum information environment know fire essence fire synchronize integrate available joint multinational capability across domain create precisely synchronize domain superiority preserve military force freedom action enable joint multinational force maneuver admiral harry harris commander pacific command uspacom identify must bring army rest joint force together sensor fire advance help overcome operational challenge face environment admiral harris previously allude fire context much traditional cannon rocket missile capability normally associate fire include capability air maritime cyber space domain part available fire suite commander']
A11: 8 | B11: Strategic Command, Technology, and Multi-Domain Warfare | C11: Additive Manufacturing Technologies | D11: G2 | E11: 64 | F11: 8_manufacture_print_technology_produce | G11: ['manufacture', 'print', 'technology', 'produce', 'supply', 'process', 'product', 'industry', 'dod', 'benefit'] | H11: ['material jet sheet lamination process create product different attribute variety purpose one application print repair part demand thus streamline supply chain activity like anticipate need process order ship store part may end use second benefit rapid development design process engineer create design print model refine design base model repeat many time inexpensively allow low cost rapid design benefit additive manufacture additive manufacture benefit traditional manufacture approach additive manufacture use le material end item build add need material', 'industrial personal printer sell typical machine capable one form additive manufacture machine available configuration capability embed electronic mechanical function final ability integrate traditional production method unlikely additive manufacture replace traditional process time near future essential two integrate improve overall industry already produce complex machine combine additive manufacture process computer numerical control machine hybrid equipment take advantage additive subtractive complex machine use best element additive subtractive manufacture process produce precise final product basic understand additive manufacture principle capability resource require operation paper discus additive manufacture assist maintain america military technological dominance improve army unit readiness maintain technological advantage note additive manufacture four primary end use rapid prototyping rapid tool direct digital manufacture maintenance rapid prototyping rapid tool play significant role assist army ability maintain technological dominance near peer competitor additive manufacture stimulate innovation design process longer hamper limitation traditional manufacture rapid prototyping provide significant improvement conventional research development process use traditional manufacture process rapid prototyping additive manufacture design often iterative form fit functional test combination thereof traditional manufacture process produce prototype represent significant investment time cost due retool manufacture equipment small run prototype since form fit functional test typically iterative process time money associate change limit experimentation necessary maintain technological additive manufacture allow engineer quickly redesign component without wait month traditional method produce prototype reduce product development cycle key component spawn innovation maintain technological dominance defense acquisition standpoint additive manufacture would speed milestone approval industry team produce competitive prototype technology maturation risk reduction competitive prototype technology maturation risk reduction faster development cycle quicker acquisition process enable army stay ahead competitor army continue work next generation capability competitor still reverse engineer current capability design initial response', 'additive manufacture often reference print innovative technology change way industry produce variety product provide ability print part assembly well large size prototype print example unite state air force use print produce part aircraft especially hard get part age equipment like unite state marine corp also first print ammunition weapon part recently add print fully operational unman aircraft system uas drone print technology allow print function system one process mean electrical circuitry incorporate benefit find across civilian industry include lower cost small quantity speed final product customer customization strong lightweight additive manufacture provide military benefit increase effectiveness efficiency expeditionary often remote operation face global military force present many challenge additive manufacture help mitigate military benefit lower cost achieve economy scale part mean print efficient low demand item current manufacture process military also gain efficiency reduce cost produce variety part one system rather nato member could use technology manufacture many type product various quantity use manufacture printer system']
A12: 9 | B12: Operational Readiness and Reserve Mobilization | C12: Mobilization Processes for Reserves | D12: G1 | E12: 57 | F12: 9_mobilization_mfgi_unit_mobilize | G12: ['mobilization', 'mfgi', 'unit', 'mobilize', 'mfgis', 'requirement', 'army', 'deployment', 'reserve', 'civilian'] | H12: ['mobilization operation capability gap pace item n china event conflict china possibility mobilization operation lsmo become reality reserve infantry regiment fill two capability gap immediately activation regard lsmo two gap lsmos need mobilization support force msf assist unit au force mobilization force generation installation mfgis expansion create cadre structure additionally use regiment capacity align force generation force pool component rearmm army reserve mission force army mobilization include activate part reserve component assemble organize army resource extend term service expand train six level mobilization reserve component range select mobilization model use past twenty year war iraq afghanistan total mobilization mobilization army reserve army national guard force critical half total army force reside two component army reserve army national guard unit mobilize mfgi purpose mfgi conduct soldier readiness process equipment issue train prior deployment past twenty year conflict due ability schedule deployment rotation army able process soldier per year use ten mfgis peak army maintain two active mfgis present mobilization occur', 'current mobilization force generation installation mfgi plan identify contingency installation handle increase volume mobilization operation may require however need significant investment mfgi meet force deployment data requirement combatant commander rand study identify desirable recommendation improve readiness reserve force preemptive investment couple early mobilization sequence priority reserve unit study clearly suggest bias toward focus train contingency source readily deployable unit reserve component greatly increase ability contribute early phase future combat operation fund constraint imperfect information mobilize key unit may make train readiness reserve force preemptive investment couple early imperfect information mobilize key unit may make train source recommendation impractical implement paper propose department defense address six strategic need ensure efficient mobilization operation credible mobilization force generation installation department defense army total force maximize effective use reserve component mobilization authority level mobilization leverage alternate mobilization sit include home station mobilization mobilization hybrid approach operate functional mobilization force generation installation expand civilian hire contract increase continuity reallocation deployable readiness invest mobilization force generation installation exist army total force infrastructure improve container management better meet mobilization operation requirement win fight fight improve nation ability mobilize deploy force rapidly critical meet combatant commander mission requirement nation ability achieve require national objective army must anticipate change operational environment contest homeland well area combat operation', 'current mobilization force generation installation mfgi plan identify contingency installation handle increase volume mobilization operation may require however need significant investment mfgi meet force deployment data requirement combatant commander rand study identify desirable recommendation improve readiness reserve force preemptive investment couple early mobilization sequence priority reserve unit study clearly suggest bias toward focus train contingency source readily deployable unit reserve component greatly increase ability contribute early phase future combat operation fund constraint imperfect information mobilize key unit may make train readiness reserve force preemptive investment couple early imperfect information mobilize key unit may make train source recommendation impractical implement paper propose department defense address six strategic need ensure efficient mobilization operation credible mobilization force generation installation department defense army total force maximize effective use reserve component mobilization authority level mobilization leverage alternate mobilization sit include home station mobilization mobilization hybrid approach operate functional mobilization force generation installation expand civilian hire contract increase continuity reallocation deployable readiness invest mobilization force generation installation exist army total force infrastructure improve container management better meet mobilization operation requirement win fight fight improve nation ability mobilize deploy force rapidly critical meet combatant commander mission requirement nation ability achieve require national objective army must anticipate change operational environment contest homeland well area combat operation']
A13: 10 | B13: Operational Readiness and Reserve Mobilization | C13: Army Reserve and Active Component Integration | D13: G1 | E13: 52 | F13: 10_army_arng_reserve_readiness | G13: ['army', 'arng', 'reserve', 'readiness', 'ac', 'component', 'combat', 'usar', 'operation', 'policy'] | H13: ['report documentation page war afghanistan wind resource shrink army reserve component rc utilize le operational overseas mission subject another round sequestration army force make drastic cut negatively impact ability support security interest thesis paper contend army senior leader rethink strategy continue use rc operational strategic reserve order maintain readiness capability capacity le cost paper present strategic consideration senior leader think balance force mix response budget constraint increase demand future force around globe strategic consideration advocate continue use rc operational mission help army cut cost meet global demand force paper also make five recommendation could help army develop total force culture better integrate rc ac force mix sequestration budget cut operationalizing reserve total force policy strategic consideration continue operational use reserve lieutenant colonel brett criqui unite state army adrian wolfberg department national security strategy project adviser abstract title strategic consideration continue operational use reserve key term force mix sequestration budget cut operationalizing reserve total force policy war afghanistan wind resource shrink army reserve component rc utilize le operational overseas mission subject another round sequestration army force make drastic cut negatively impact ability support security interest', 'total force ac rc provide operational capability strategic depth meet defense homeland security currently discussion washington various level proportional reduction three component austere proposal may reduce national defense capability put homeland security emergency domestic response risk time different approach capitalize cost effectiveness national congress decision reduce active army end strength require army national guard arng fill readiness loss remain healthy vibrant force capable sustain involvement overseas research focus research paper provide solution current arng operational obstacle direction future national guard role support combatant commander state governor national guard strategic reserve throughout cold war war period reserve component unite state organize strategic reserve primary conceptual mission expand arm force rapidly event time frame arng require long mobilization timeline order build readiness necessary respond national security crisis arng inability mobilize deploy unit efficient timeline make individual soldier augmentation norm vietnam arng unit remain competent traditional effectively natural catastrophe event february general creighton abrams army chief staff testify house arm service committee general abrams express key point support need improve rc readiness support strong security posture army maintain peacetime deterrent force structure sufficient size quality readiness use manpower efficiently', 'fund project allocate army base operate budget continue deployment arng usar unit support operational overseas mission many advocate arng usar worry without rc involvement operational overseas mission army may reduce budget last decade war army go great length ensure better access rc development new rotational deployment policy include authority title section secretary army call rc soldier support preplanned name mission requirement combatant currently authority combatant commander ccdrs call rc unit support unplanned operation around therefore army senior leader choose instead resource rc strategic force rely ac overseas contingency steady state historically rc unit allow mobilize authority presidential take time get mobilization authority still valid utilize time major war crisis federalize rc mobilization authority new authority streamline process help make rc responsive contingency without fund mobilization authority rc afford opportunity conduct operational overseas mission could negatively impact readiness equipment modernization retention place stress already overstretch ac force second another major factor must ignore senior leader critical capability equipment rc longer exist ac due recent transformation effort force structure currently rc percent transportation capability percent engineer percent medical capability military police logistics enable capability example army light medium truck company reside rc additionally percent army aviation man unman aircraft reside limit amount troop move air ccdr area responsibility aor early surge forward presence operational requirement present another problem longer ignore army senior leader much army combat combat support capability conduct operational mission resident rc rc army connection america gen abrams know take first step integrate ac rc initiation total force policy']
... A23: 20 | B23: Operational Readiness and Reserve Mobilization | C23: Equipment Maintenance and Deployment Support | D23: G1 | E23: 25 | F23: 20_equipment_maintenance_support_modernization | G23: ['equipment', 'maintenance', 'support', 'modernization', 'sustainment', 'readiness', 'army', 'organization', 'deploy', 'ammunition'] | H23: ['consistently predictably equip priority distribution new combat serviceable equipment associate support test equipment shall give unit schedule mission deployment employment first regardless component rc equipment level highest level history however postwar fiscal constraint bring significant equip challenge next several year september congress mandate dod create process policy directive ensure transparency financial accountability require fund intend rc get transparency define dod refer visibility traceability track requirement program fund contract production delivery army procurement item army continue endeavor support dod effort increase transparency usar instance provide critical portion army contingency response force operationally adaptive capability focus combat support combat service support one readiness goal ensure interoperability joint interagency intergovernmental multinational jiim partner support global operation essential usar support mission hd defense support civil authority contingency operation theater chief army reserve lieutenant general jeffrey talley write testimony house arm service subcommittee tactical air land force reemphasized need ready train equip army reserve partnership army army reserve make great stride fill equipment shortage since increase equipment hand today addition critical dual use cdu equipment hand equipment use warfight domestic support modernization rc equipment remain challenge even high overall equipment level usar arng modern equipment level lag behind ac counterpart respectively', 'army transform maintenance structure reduce redundancy provide forward repair capability include sustainment theater combat formation army field support brigade afsb consist small staff rely civilian logistics augmentation representative contract maintenance worker augment unit field maintenance activity provide sustainment maintenance combat afsb provide capability reach force reduction measure need large army force drawdowns afsb vital component manage battlefield maintenance sustainment footprint widely use iraq afghanistan afsbs rely contract maintenance workforce minimal military workforce oversight recent conflict augment civilian workforce ensure maintenance repair forward equipment reduce military maintenance activity deployment reduce operational tempo active duty reserve force reliance contractor support lead overreliance contractor support instead rely organic depot provide surge capability generate combat forward repair activity work guidance afsb deploy life cycle management command direction recent example ability provide forward support deploy forward repair activity support kuwait tobyhanna army depot communication equipment extend depot support theater repair activity enable quicker repair equipment immediate return user increase combat capability mature theater forward repair activity help reduce cost improve operational readiness sustainment equipment', 'specifically must examine number allocate resource maintenance organization within division area resourcing employment sustainment level maintenance activity expeditionary operation one army solution invest maintenance force structure reduce risk combat formation ability sustain equipment grind combat operation without return redundancy unit cold army reinvesting maintenance force structure division level still investment go far enough address gap prepare scale grind combat operation army capability integration center arcic validate requirement maintenance surge team field maintenance company division sustainment battalion add platoon combat system mechanic support armor stryker concept paper force design update fdu currently staff army staff explain purpose force design change provide maintenance capability company division sustainment battalion add platoon combat system mechanic support armor stryker formation concept paper force design update fdu currently staff army staff explain purpose force design change provide maintenance capability capacity surge modularly configure maintenance team towards critical point need within armor stryker brigade combat team area operation order support effort generation combat power decisive action approve implement fdu add platoon soldier associate equipment fiscal year allow division sustainment brigade surge maintenance capacity forward unit fdu go far enough provide total amount maintainer necessary make decrement support force attrited force drawdowns past two decade add small maintenance capability active army force structure division level add combat system repair capability army national guard additionally fdu attempt solve army lack maintenance asset problem division level']

Sheet table_info
B2: Sub-Topic ID | C2: Sub-Topic (Interpreted Label) | D2: Sub-Topic Keywords | E2: Paragraph Count
B3: WT0 | C3: Command Philosophy and Leadership Doctrine | D3: ['command', 'army', 'commander', 'leadership', 'doctrine', 'subordinate', 'operation', 'philosophy', 'initiative', 'strategic'] | E3: 343
B4: WT1 | C4: Unmanned Aerial Systems and Aviation Tech | D4: ['uas', 'aircraft', 'aviation', 'unman', 'drone', 'technology', 'army', 'aerial', 'pilot', 'swarm'] | E4: 322
B5: WT2 | C5: Headquarters Operations and Integration | D5: ['operation', 'headquarter', 'commander', 'support', 'function', 'component', 'base', 'army', 'integrate', 'corp'] | E5: 119
B6: WT3 | C6: National Guard and Reserve Components | D6: ['guard', 'reserve', 'army', 'component', 'militia', 'readiness', 'increase', 'general', 'federal', 'unit'] | E6: 90
B7: WT4 | C7: Regional Alignment and Funding Support | D7: ['raf', 'alignment', 'division', 'operation', 'support', 'military', 'commander', 'region', 'fund', 'requirement'] | E7: 86
B8: WT5 | C8: Defense Logistics and Enterprise Management | D8: ['logistics', 'logistician', 'management', 'dod', 'dla', 'defense', 'enterprise', 'strategy', 'army', 'operation'] | E8: 78
B9: WT6 | C9: Unit Training and Readiness Cycle | D9: ['readiness', 'unit', 'train', 'army', 'rc', 'reserve', 'resource', 'deployment', 'equipment', 'arforgen'] | E9: 75
B10: WT7 | C10: Multi-Domain Operations Concepts | D10: ['domain', 'mdo', 'operation', 'enemy', 'concept', 'maneuver', 'space', 'military', 'intelligence', 'battle'] | E10: 74
B11: WT8 | C11: Additive Manufacturing Technologies | D11: ['manufacture', 'print', 'technology', 'produce', 'supply', 'process', 'product', 'industry', 'dod', 'benefit'] | E11: 64
B12: WT9 | C12: Mobilization Processes for Reserves | D12: ['mobilization', 'mfgi', 'unit', 'mobilize', 'mfgis', 'requirement', 'army', 'deployment', 'reserve', 'civilian'] | E12: 57
B13: WT10 | C13: Army Reserve and Active Component Integration | D13: ['army', 'arng', 'reserve', 'readiness', 'ac', 'component', 'combat', 'usar', 'operation', 'policy'] | E13: 52
B14: WT11 | C14: Domain Warfare and Artillery Operations | D14: ['force', 'domain', 'warfare', 'army', 'operation', 'russia', 'mdo', 'artillery', 'fight', 'area'] | E14: 52
... B23: WT20 | C23: Equipment Maintenance and Deployment Support | D23: ['equipment', 'maintenance', 'support', 'modernization', 'sustainment', 'readiness', 'army', 'organization', 'deploy', 'ammunition'] | E23: 25

Sheet document_topic_assignments
A1: Year | B1: Filename | C1: Paragraph | D1: Topic | E1: Paragraph_Length | F1: Theme | G1: Topic Interpretation | H1: Group
A2: 2014 | B2: doc_AY2014_001_para_0_0.txt | C2: report documentation page throughout course airpower relatively short history usaf use otherwise peaceful period as adjust strategic philosophy equipment combat operation afghanistan presumably draw end usaf intend reshape rebalance force divest warthog favor joint strike fighter purpose paper highlight impact divestment consider alternative maintain close air support primacy use key criterion distil historical review paper compare three potential combat air force unit ca platform usaf organize train equip successfully conduct ca arm historically find criterion service commitment culture platform capability force readiness air force acquire suitable ca replacement platform however give fiscal reality feasible alternative specifically task proportion squadron ca mission divestiture impact option maintain ca primacy lieutenant colonel matthew villella unite state air force colonel timothy brown department military strategy plan operation project adviser abstract title divestiture impact option maintain ca primacy key term close air support force relation attack throughout course airpower relatively short history usaf use war otherwise peaceful period as adjust strategic philosophy equipment combat operation afghanistan presumably draw end usaf intend reshape rebalance force divest warthog favor joint strike fighter purpose paper highlight impact divestment consider alternative maintain close air support primacy | D2: 10 | E2: 187 | F2: =VLOOKUP(D2, topic_info!$A$2:$H$23, 2, FALSE) -> Operational Readiness and Reserve Mobilization | G2: =VLOOKUP($D2, topic_info!$A$2:$H$23, 3, FALSE) -> Army Reserve and Active Component Integration | H2: =VLOOKUP($D2, topic_info!$A$2:$H$23, 4, FALSE) -> G1
A3: 2014 | B3: doc_AY2014_001_para_0_1.txt | C3: end call action patrol sky bosnia serbia warthog enable international ever precision efficiency turn millennium thunderbolt ii pilot continue receive praise worthy numerous distinguish fly cross receive operation endure iraqi freedom yet smolder fire ca value necessity would return rebecca grant director washington security forum recently state great build airborne cannon fighter today go forward need ability modern sensor really retrofit onto give fiscal environment budget control act bca air force senior leader convince divest matter accord air force official divest fleet save approximately course next five year however procurement fighter require approximately time thus many surmise former assistant secretary navy acquisition executive everett pyatt state retain fleet would cost billion would eliminate need save pentagon billion furthermore accord air force total ownership cost aftoc program data cheapest operate aircraft currently inventory conduct ca therefore divest appear provide advance technology capability mean achieve control air way vice fiscal necessity perhaps review historical document serve draw implication divest platform solely dedicate ca instruct best organize train equip service without ca history commitment culture capability train consider general air support grind force prime mission function however middle strategic think advance air defense technology increase mission begin dilute air support culture early air leader | D3: 1 | E3: 201 | F3: =VLOOKUP(D3, topic_info!$A$2:$H$23, 2, FALSE) -> Strategic Command, Technology, and Multi-Domain Warfare | G3: =VLOOKUP($D3, topic_info!$A$2:$H$23, 3, FALSE) -> Unmanned Aerial Systems and Aviation Tech | H3: =VLOOKUP($D3, topic_info!$A$2:$H$23, 4, FALSE) -> G2
A4: 2014 | B4: doc_AY2014_001_para_0_2.txt | C4: large part due longstanding belief war grind future conflict prevent primarily standoff technology weapon u army marine corp special operation force adapt hone ca plan capability last triad insist operation land domain effective achieve human outcome prerequisite achieve national objective national guard chief general frank grass sum concern ca enthusiast army guy tell close army wonder mission nevertheless usaf plan retire face budget pressure advance proliferate technology strategic call prioritize quadrennial defense review demand global power particularly advance modern air defense system give history reveal necessity commitment culture platform capability readiness provide effective ca usaf must determine alternative method organize train equip next generation successfully conduct mission history thus deem necessary word fehrenbach may fly land forever may bomb atomize pulverize wipe clean desire defend protect keep civilization must grind way roman legion put young men mud assume corporate usaf decision retire succumb political pressure paper consider three primary alternative usaf could employ maintain ca primacy without principle purpose alternative must ensure chief staff air force csaf general mark welsh state mission continue get effectively efficiently first alternative quite simply status quo utilize platform replace manner replace many unit late second air force could organize specifically task proportion unit ca finally air force could develop procure dedicate ca platform replace | D4: 1 | E4: 210 | F4: =VLOOKUP(D4, topic_info!$A$2:$H$23, 2, FALSE) -> Strategic Command, Technology, and Multi-Domain Warfare | G4: =VLOOKUP($D4, topic_info!$A$2:$H$23, 3, FALSE) -> Unmanned Aerial Systems and Aviation Tech | H4: =VLOOKUP($D4, topic_info!$A$2:$H$23, 4, FALSE) -> G2
A5: 2014 | B5: doc_AY2014_001_para_0_4.txt | C5: history date back world war ii wing pursuit group showcased phantom vietnam eagle crisis grenada panama desert storm post nomad provide arm throughout north america operation noble eagle secure two president unite state multiple space shuttle fighter wing recent culture one air superiority large part due airpower legacy airman believe control air generally control surface therefore dominant platform must emphasize expend resource support offensive counterair oca defensive counterair dca suppression embed mechanism likely disappear heritage air superiority attack phrase signify grind support culture unit command general staff college student major michael ford conduct comparative analysis platform combat performance unsurprisingly conclude fighter force consistently outperform effective conduct combat operation although quantitative ca fighter force would likewise expect outperform force however accord rebecca grant numerous others specifically design unravel integrate air defense certain sensor capability enable higher situational awareness round millimeter might consider significant liability conduct ca compare course last decade gun provide pilot ability achieve timely effect otherwise accord draft rtm ca train mission account le overall regular air force pilot annual train equivalent one ca mission every month stark contrast rtm require four time amount train sortie per pilot per year nearly two per importantly lack require train jsf equally hinder jtac train provide le ca exposure command control intelligence surveillance reconnaissance joint force writ large comparison flight event task respective rtms reveal broader impact train | D5: 1 | E5: 226 | F5: =VLOOKUP(D5, topic_info!$A$2:$H$23, 2, FALSE) -> Strategic Command, Technology, and Multi-Domain Warfare | G5: =VLOOKUP($D5, topic_info!$A$2:$H$23, 3, FALSE) -> Unmanned Aerial Systems and Aviation Tech | H5: =VLOOKUP($D5, topic_info!$A$2:$H$23, 4, FALSE) -> G2
A6: 2014 | B6: doc_AY2014_001_para_0_5.txt | C6: platform maintain culture support grind force else furthermore one seven essential condition effective ca air therefore ca platform need posse capability diminish focus mission support grind force ca capability design platform train would predominantly devote ca thus better enable readiness joint force finally procurement new ca platform could numerous ancillary benefit service nation build partner however alternative incur relatively high cost without sacrifice current air force budget feasible recommendation risk air force thoroughly invest production joint strike fighter fundamental assumption despite divestiture usaf must ca mission best alternative achieve ca primacy mean platform replace light fiscal reality current challenge start new program highly unlikely short term therefore specifically task proportion unit ca mission best alternative currently deem feasible | D6: 1 | E6: 118 | F6: =VLOOKUP(D6, topic_info!$A$2:$H$23, 2, FALSE) -> Strategic Command, Technology, and Multi-Domain Warfare | G6: =VLOOKUP($D6, topic_info!$A$2:$H$23, 3, FALSE) -> Unmanned Aerial Systems and Aviation Tech | H6: =VLOOKUP($D6, topic_info!$A$2:$H$23, 4, FALSE) -> G2
A7: 2014 | B7: doc_AY2014_003_para_2_12.txt | C7: report documentation page additive manufacture commonly refer print one many future innovation initiative army must leverage next year quest maintain adaptive agile edge adversary paper examine possible future army implementation additive manufacture ensure army depend possible title responsibility special operation force sister service others agility period conflict early entry support humanitarian relief operation paper conclude address specific aspect doctrine organization train materiel leadership education personnel facility policy recommendation need execute cohesive implementation additive manufacture usawc civilian research project additive manufacture within army ensure future agility colonel jam becker unite state army chris caplice massachusetts institute technology project adviser colonel dave dworak army war college faculty mentor abstract additive manufacture commonly refer print one many future innovation initiative army must leverage next year quest maintain adaptive agile edge adversary paper examine possible future army implementation additive manufacture ensure army depend possible title responsibility special operation force sister service others agility period conflict early entry support humanitarian relief operation paper conclude address specific aspect doctrine organization train materiel leadership education personnel facility policy recommendation need execute cohesive implementation additive manufacture additive manufacture within army ensure future agility september article lexington institute early warn blog title military must integrate forward presence crisis response expeditionary warfare mission daniel goure state forward presence prove insufficient prevent crisis occur | D7: 10 | E7: 213 | F7: =VLOOKUP(D7, topic_info!$A$2:$H$23, 2, FALSE) -> Operational Readiness and Reserve Mobilization | G7: =VLOOKUP($D7, topic_info!$A$2:$H$23, 3, FALSE) -> Army Reserve and Active Component Integration | H7: =VLOOKUP($D7, topic_info!$A$2:$H$23, 4, FALSE) -> G1
A8: 2014 | B8: doc_AY2014_003_para_2_13.txt | C8: principle provide greatest dramatic benefit use whole much research discussion within paper also touch principle manufacture complexity free traditional manufacture complicate object shape cost make printer complexity cost simplicity fabricate ornate complicate shape require time skill cost print simple block free complexity disrupt traditional price model change calculate cost manufacture thing | D8: 8 | E8: 51 | F8: =VLOOKUP(D8, topic_info!$A$2:$H$23, 2, FALSE) -> Strategic Command, Technology, and Multi-Domain Warfare | G8: =VLOOKUP($D8, topic_info!$A$2:$H$23, 3, FALSE) -> Additive Manufacturing Technologies | H8: =VLOOKUP($D8, topic_info!$A$2:$H$23, 4, FALSE) -> G2
A9: 2014 | B9: doc_AY2014_003_para_2_14.txt | C9: zero skill manufacture traditional artisan train apprentice year gain skill need mass production computer guide manufacture machine diminish need skilled production however traditional manufacture machine still demand skilled expert adjust calibrate printer get guidance design file make object equal complexity printer require le operator skill injection mold machine unskilled manufacture open new business model could offer new mode production people remote environment extreme circumstance | D9: 8 | E9: 64 | F9: =VLOOKUP(D9, topic_info!$A$2:$H$23, 2, FALSE) -> Strategic Command, Technology, and Multi-Domain Warfare | G9: =VLOOKUP($D9, topic_info!$A$2:$H$23, 3, FALSE) -> Additive Manufacturing Technologies | H9: =VLOOKUP($D9, topic_info!$A$2:$H$23, 4, FALSE) -> G2
A10: 2014 | B10: doc_AY2014_003_para_2_15.txt | C10: scan technology print together introduce high resolution shapeshifting physical digital world scan edit duplicate physical object create exact replica improve many principle already hold true today others come true come september paper title game changer disruptive technology defense strategy author state additive manufacture could fundamentally impact defense industrial base manufacture process writ large dramatically increase pace move prototype production enhance flexibility adaptability production line go describe litany change could address technology include small batch development major platform design adjustment base external factor environment countermeasure discus logistical implication additive manufacture forward deploy unit base ability print part available material opportunity discus use additive manufacture humanitarian assistance mission current tactical application combat operation numerous point raise article really highlight significance adaptability begin continue provide u army within army industrial base flexibility adaptability print critically require item forward deploy set would allow smaller stock repair part well ability alter make engineer correction change exist part equipment give operational need unit grind army strive make leaner lighter mobile effective force rapidly become tool leverage army help meet requirement regardless type location operation raise question industry today relation army department defense whole incorporation disruptive technology operation u army war college civilian research project colonel jon drushal discus implication army organic industrial base aoib | D10: 8 | E10: 208 | F10: =VLOOKUP(D10, topic_info!$A$2:$H$23, 2, FALSE) -> Strategic Command, Technology, and Multi-Domain Warfare | G10: =VLOOKUP($D10, topic_info!$A$2:$H$23, 3, FALSE) -> Additive Manufacturing Technologies | H10: =VLOOKUP($D10, topic_info!$A$2:$H$23, 4, FALSE) -> G2
A11: 2014 | B11: doc_AY2014_003_para_2_16.txt | C11: impact three emerge technology manufacture define execute management software data file serve impetus move industry hardware base supply chain supply factor cite drive change scale location volume three factor cause supply chain become simple flexible localize additionally ibm predict change supply chain lead average save per unit effort company like ibm provide complementary technology assist rapid development exponential use across multiple industry direct application print department defense u department defense army sister service navy air force specifically show greater interest tactical forward position usage printer army rapid equip force deployment mobile expeditionary lab afghanistan july contain lab cost million dollar apiece build within standard ship container man contract engineer army soldier end prototyping machine lab gear manufacture although army maintain capability kandahar bagram airfield afghanistan deployment two three mobile lab location international security assistance force isaf regional command east regional command south afghanistan push capability furthest forward deployment lab already help provide material solution several issue likely continue throughout length usage afghanistan lab could also send execute similar mission dod support humanitarian crisis joint train scenario small scale mission maintain large repair part depot component storage unrealistic simply expensive decision army publish january memorandum secretary army joseph westphal make rapid equip force endure element several use department defense note october article title pentagon plan printer mobile lab bomb sniffer prototype limb article robert beckhusen highlight several recent time action various army dod entity regard one point article previously address paper deployment ref mobile expeditionary lab | D11: 8 | E11: 245 | F11: =VLOOKUP(D11, topic_info!$A$2:$H$23, 2, FALSE) -> Strategic Command, Technology, and Multi-Domain Warfare | G11: =VLOOKUP($D11, topic_info!$A$2:$H$23, 3, FALSE) -> Additive Manufacturing Technologies | H11: =VLOOKUP($D11, topic_info!$A$2:$H$23, 4, FALSE) -> G2
A12: 2014 | B12: doc_AY2014_003_para_2_17.txt | C12: engineer ulrich eidenschink become significant production method build model manufacture part piece could become part soldier central issue facility cif record transit one post another would also provide unit commander ability rapidly tool grip break deployment tactical train would nothing replication army produce contact glass individual soldier current centralize medical facility recommendation requirement replacement part future contract negotiation company provide equipment hardware army many company already process use manufacture process part component company already establish manufacture method ge intellectual property right requirement must incorporate future contract negotiation program record begin production regardless whether company begin develop computer aid design cad file replacement part incorporate requirement future contract army position rapidly incorporate innovative technology field environment could ultimately incur higher cost later date army seek get data question | D12: 8 | E12: 127 | F12: =VLOOKUP(D12, topic_info!$A$2:$H$23, 2, FALSE) -> Strategic Command, Technology, and Multi-Domain Warfare | G12: =VLOOKUP($D12, topic_info!$A$2:$H$23, 3, FALSE) -> Additive Manufacturing Technologies | H12: =VLOOKUP($D12, topic_info!$A$2:$H$23, 4, FALSE) -> G2
A13: 2014 | B13: doc_AY2014_004_para_3_18.txt | C13: report documentation page equipment army field grow complex require hour train soldier master skill decay time require frequent refresher train amount equipment per soldier per unit also increase together three trend place increase train burden unit burden may force reduce time spend collective train make room increase task take shortcut equipment train new equipment may increase unit effectiveness much plan instance may even reduce problem particularly important resource fall army force structure fall current strategy call army unit proficient wider array task past decisive action stability operation build partner capacity | D13: 20 | E13: 90 | F13: =VLOOKUP(D13, topic_info!$A$2:$H$23, 2, FALSE) -> Operational Readiness and Reserve Mobilization | G13: =VLOOKUP($D13, topic_info!$A$2:$H$23, 3, FALSE) -> Equipment Maintenance and Deployment Support | H13: =VLOOKUP($D13, topic_info!$A$2:$H$23, 4, FALSE) -> G1
... A2341: 2024 | B2341: doc_AY2024_223_para_3435_24105.txt | C2341: loss fund represent loss train dollar loss fund repair part loss fund fuel year national guard unit could absorb fund loss demand increase detrimental effect increase well increase demand equate equipment usage fund divert reimbursement process keep earlier example mind identify trend might help forecast demand national guard dsca support identify effect lose fund follow national guard support state request must also look trend might accentuate issue two identifiable trend potential add issue involve climate change federal budget constraint first help forecast probability future event would result state request support national guard include probability number future event also size scope future event | D2341: 3 | E2341: 102 | F2341: =VLOOKUP(D2341, topic_info!$A$2:$H$23, 2, FALSE) -> Operational Readiness and Reserve Mobilization | G2341: =VLOOKUP($D2341, topic_info!$A$2:$H$23, 3, FALSE) -> National Guard and Reserve Components | H2341: =VLOOKUP($D2341, topic_info!$A$2:$H$23, 4, FALSE) -> G1
